{
	"Version": 3,
	"Meta": {
		"Duration": 2.67,
		"Fps": 30.0,
		"Loop": true,
		"AreBeziersRestricted": true,
		"CurveCount": 55,
		"TotalSegmentCount": 87,
		"TotalPointCount": 206,
		"UserDataCount": 0,
		"TotalUserDataSize": 0
	},
	"Curves": [
		{
			"Target": "Model",
			"Id": "Opacity",
			"Segments": [
				0,
				1,
				0,
				2.67,
				1
			]
		},
		{
			"Target": "Parameter",
			"Id": "ParamBodyAngleX",
			"Segments": [
				0,
				0,
				1,
				0.167,
				0,
				0.333,
				10,
				0.5,
				10,
				0,
				2.667,
				10
			]
		},
		{
			"Target": "Parameter",
			"Id": "ParamAngleY",
			"Segments": [
				0,
				0,
				1,
				0.167,
				0,
				0.333,
				21,
				0.5,
				21,
				0,
				2.667,
				21
			]
		},
		{
			"Target": "Parameter",
			"Id": "ParamAngleZ",
			"Segments": [
				0,
				0,
				0,
				2.667,
				0
			]
		},
		{
			"Target": "Parameter",
			"Id": "ParamEyeLOpen",
			"Segments": [
				0,
				1,
				1,
				0.133,
				1,
				0.267,
				0,
				0.4,
				0,
				1,
				0.6,
				0,
				0.8,
				1,
				1,
				1,
				1,
				1.167,
				1,
				1.333,
				0,
				1.5,
				0,
				1,
				1.778,
				0,
				2.056,
				1,
				2.333,
				1,
				0,
				2.667,
				1
			]
		},
		{
			"Target": "Parameter",
			"Id": "ParamEyeROpen",
			"Segments": [
				0,
				1,
				1,
				0.133,
				1,
				0.267,
				0,
				0.4,
				0,
				1,
				0.6,
				0,
				0.8,
				1,
				1,
				1,
				1,
				1.167,
				1,
				1.333,
				0,
				1.5,
				0,
				1,
				1.778,
				0,
				2.056,
				1,
				2.333,
				1,
				0,
				2.667,
				1
			]
		},
		{
			"Target": "Parameter",
			"Id": "ParamMouthForm",
			"Segments": [
				0,
				-1,
				1,
				0.167,
				-1,
				0.333,
				-1,
				0.5,
				-1,
				0,
				2.667,
				-1
			]
		},
		{
			"Target": "Parameter",
			"Id": "ParamMouthOpenY",
			"Segments": [
				0,
				0,
				0,
				2.667,
				0
			]
		},
		{
			"Target": "Parameter",
			"Id": "ParamBreath",
			"Segments": [
				0,
				0,
				0,
				2.667,
				0
			]
		},
		{
			"Target": "Parameter",
			"Id": "ParamEyeLSmile",
			"Segments": [
				0,
				0,
				0,
				2.667,
				0
			]
		},
		{
			"Target": "Parameter",
			"Id": "ParamEyeRSmile",
			"Segments": [
				0,
				0,
				0,
				2.667,
				0
			]
		},
		{
			"Target": "Parameter",
			"Id": "ParamEyeBallX",
			"Segments": [
				0,
				0,
				1,
				0.167,
				0,
				0.333,
				1,
				0.5,
				1,
				0,
				2.667,
				1
			]
		},
		{
			"Target": "Parameter",
			"Id": "ParamEyeBallY",
			"Segments": [
				0,
				0,
				1,
				0.167,
				0,
				0.333,
				0.5,
				0.5,
				0.5,
				0,
				2.667,
				0.5
			]
		},
		{
			"Target": "Parameter",
			"Id": "ParamBrowRY",
			"Segments": [
				0,
				0,
				1,
				0.167,
				0,
				0.333,
				-1,
				0.5,
				-1,
				0,
				2.667,
				-1
			]
		},
		{
			"Target": "Parameter",
			"Id": "ParamBrowLY",
			"Segments": [
				0,
				0,
				1,
				0.167,
				0,
				0.333,
				-1,
				0.5,
				-1,
				0,
				2.667,
				-1
			]
		},
		{
			"Target": "Parameter",
			"Id": "ParamBrowLX",
			"Segments": [
				0,
				0,
				0,
				2.667,
				0
			]
		},
		{
			"Target": "Parameter",
			"Id": "ParamBrowRX",
			"Segments": [
				0,
				0,
				0,
				2.667,
				0
			]
		},
		{
			"Target": "Parameter",
			"Id": "ParamBrowLAngle",
			"Segments": [
				0,
				0,
				1,
				0.167,
				0,
				0.333,
				1,
				0.5,
				1,
				0,
				2.667,
				1
			]
		},
		{
			"Target": "Parameter",
			"Id": "ParamBrowRAngle",
			"Segments": [
				0,
				0,
				1,
				0.167,
				0,
				0.333,
				1,
				0.5,
				1,
				0,
				2.667,
				1
			]
		},
		{
			"Target": "Parameter",
			"Id": "ParamBrowLForm",
			"Segments": [
				0,
				0,
				0,
				2.667,
				0
			]
		},
		{
			"Target": "Parameter",
			"Id": "ParamBrowRForm",
			"Segments": [
				0,
				0,
				0,
				2.667,
				0
			]
		},
		{
			"Target": "Parameter",
			"Id": "ParamCheek",
			"Segments": [
				0,
				0,
				0,
				2.667,
				0
			]
		},
		{
			"Target": "Parameter",
			"Id": "ParamAngleX",
			"Segments": [
				0,
				0,
				0,
				2.667,
				0
			]
		},
		{
			"Target": "Parameter",
			"Id": "ParamBodyAngleY",
			"Segments": [
				0,
				0,
				0,
				2.667,
				0
			]
		},
		{
			"Target": "Parameter",
			"Id": "ParamBodyAngleZ",
			"Segments": [
				0,
				0,
				0,
				2.667,
				0
			]
		},
		{
			"Target": "Parameter",
			"Id": "ParamHairFront",
			"Segments": [
				0,
				0,
				1,
				0.167,
				0,
				0.333,
				0.6,
				0.5,
				0.6,
				1,
				0.778,
				0.6,
				1.056,
				0,
				1.333,
				0,
				0,
				2.667,
				0
			]
		},
		{
			"Target": "Parameter",
			"Id": "ParamHairSide",
			"Segments": [
				0,
				0,
				1,
				0.167,
				0,
				0.333,
				0.6,
				0.5,
				0.6,
				1,
				0.778,
				0.6,
				1.056,
				0.2,
				1.333,
				0.2,
				0,
				2.667,
				0.2
			]
		},
		{
			"Target": "Parameter",
			"Id": "ParamHairBack",
			"Segments": [
				0,
				0,
				1,
				0.167,
				0,
				0.333,
				0.6,
				0.5,
				0.6,
				1,
				0.778,
				0.6,
				1.056,
				0.2,
				1.333,
				0.2,
				0,
				2.667,
				0.2
			]
		},
		{
			"Target": "Parameter",
			"Id": "Param4",
			"Segments": [
				0,
				0,
				0,
				2.667,
				0
			]
		},
		{
			"Target": "Parameter",
			"Id": "Param3",
			"Segments": [
				0,
				0,
				0,
				2.667,
				0
			]
		},
		{
			"Target": "Parameter",
			"Id": "Param",
			"Segments": [
				0,
				0,
				1,
				0.167,
				0,
				0.333,
				30,
				0.5,
				30,
				1,
				0.667,
				30,
				0.833,
				30,
				1,
				30,
				1,
				1.244,
				30,
				1.489,
				30.248,
				1.733,
				29,
				1,
				1.989,
				27.695,
				2.244,
				13,
				2.5,
				13,
				0,
				2.667,
				13
			]
		},
		{
			"Target": "Parameter",
			"Id": "Param2",
			"Segments": [
				0,
				0,
				1,
				0.167,
				0,
				0.333,
				13,
				0.5,
				13,
				1,
				1.167,
				13,
				1.833,
				0,
				2.5,
				0,
				0,
				2.667,
				0
			]
		},
		{
			"Target": "Parameter",
			"Id": "Param5",
			"Segments": [
				0,
				0,
				1,
				0.167,
				0,
				0.333,
				1,
				0.5,
				1,
				1,
				0.733,
				1,
				0.967,
				1,
				1.2,
				1,
				1,
				1.556,
				1,
				1.911,
				0,
				2.267,
				0,
				0,
				2.667,
				0
			]
		},
		{
			"Target": "Parameter",
			"Id": "Param6",
			"Segments": [
				0,
				0,
				0,
				2.667,
				0
			]
		},
		{
			"Target": "Parameter",
			"Id": "Param7",
			"Segments": [
				0,
				0,
				0,
				2.667,
				0
			]
		},
		{
			"Target": "Parameter",
			"Id": "Param9",
			"Segments": [
				0,
				0,
				0,
				2.667,
				0
			]
		},
		{
			"Target": "Parameter",
			"Id": "Param11",
			"Segments": [
				0,
				0,
				0,
				2.667,
				0
			]
		},
		{
			"Target": "Parameter",
			"Id": "Param10",
			"Segments": [
				0,
				0,
				0,
				2.667,
				0
			]
		},
		{
			"Target": "PartOpacity",
			"Id": "__RootPart__",
			"Segments": [
				0,
				1,
				0,
				2.67,
				1
			]
		},
		{
			"Target": "PartOpacity",
			"Id": "Part14",
			"Segments": [
				0,
				1,
				0,
				2.67,
				1
			]
		},
		{
			"Target": "PartOpacity",
			"Id": "Part",
			"Segments": [
				0,
				1,
				0,
				2.67,
				1
			]
		},
		{
			"Target": "PartOpacity",
			"Id": "Part2",
			"Segments": [
				0,
				1,
				0,
				2.67,
				1
			]
		},
		{
			"Target": "PartOpacity",
			"Id": "face",
			"Segments": [
				0,
				1,
				0,
				2.67,
				1
			]
		},
		{
			"Target": "PartOpacity",
			"Id": "eyes",
			"Segments": [
				0,
				1,
				0,
				2.67,
				1
			]
		},
		{
			"Target": "PartOpacity",
			"Id": "Part3",
			"Segments": [
				0,
				1,
				0,
				2.67,
				1
			]
		},
		{
			"Target": "PartOpacity",
			"Id": "Part4",
			"Segments": [
				0,
				1,
				0,
				2.67,
				1
			]
		},
		{
			"Target": "PartOpacity",
			"Id": "mouse",
			"Segments": [
				0,
				1,
				0,
				2.67,
				1
			]
		},
		{
			"Target": "PartOpacity",
			"Id": "Part5",
			"Segments": [
				0,
				1,
				0,
				2.67,
				1
			]
		},
		{
			"Target": "PartOpacity",
			"Id": "Part6",
			"Segments": [
				0,
				1,
				0,
				2.67,
				1
			]
		},
		{
			"Target": "PartOpacity",
			"Id": "Part7",
			"Segments": [
				0,
				1,
				0,
				2.67,
				1
			]
		},
		{
			"Target": "PartOpacity",
			"Id": "Part8",
			"Segments": [
				0,
				1,
				0,
				2.67,
				1
			]
		},
		{
			"Target": "PartOpacity",
			"Id": "Part9",
			"Segments": [
				0,
				1,
				0,
				2.67,
				1
			]
		},
		{
			"Target": "PartOpacity",
			"Id": "Part10",
			"Segments": [
				0,
				1,
				0,
				2.67,
				1
			]
		},
		{
			"Target": "PartOpacity",
			"Id": "Part11",
			"Segments": [
				0,
				1,
				0,
				2.67,
				1
			]
		},
		{
			"Target": "PartOpacity",
			"Id": "Part12",
			"Segments": [
				0,
				1,
				0,
				2.67,
				1
			]
		}
	]
}